otscomics/__init__.py
otscomics-0.1.0.dist-info/LICENSE
otscomics-0.1.0.dist-info/METADATA
otscomics-0.1.0.dist-info/WHEEL
otscomics-0.1.0.dist-info/top_level.txt
otscomics-0.1.0.dist-info/RECORD
